[
  {
    "uid": "43970566-ee54-4d65-8171-63b88c8a45f4",
    "text": "Uriel",
    "read": true,
    "created_at": "305"
  },
  {
    "uid": "eba4a65a-ea8c-44bc-9f91-a35ce972d248",
    "text": "Gusti",
    "read": true,
    "created_at": "449"
  },
  {
    "uid": "abe7089e-d19a-408a-b28b-f121a85c7392",
    "text": "Shirlee",
    "read": false,
    "created_at": "623"
  },
  {
    "uid": "595d7d16-3d30-4e7e-b777-13f371c3ca5c",
    "text": "Reba",
    "read": true,
    "created_at": "879"
  },
  {
    "uid": "68e6d597-0e33-4e8e-af9e-d7ce04f68790",
    "text": "Miller",
    "read": false,
    "created_at": "518"
  },
  {
    "uid": "70d7e685-cd7e-419a-8fcb-42ab825b64e1",
    "text": "Cletus",
    "read": true,
    "created_at": "434"
  },
  {
    "uid": "6cc36330-9f81-4a7f-9914-5516c3479446",
    "text": "Jandy",
    "read": false,
    "created_at": "388"
  },
  {
    "uid": "8c056dda-f055-4ab6-ac27-44470bee2a63",
    "text": "Corri",
    "read": true,
    "created_at": "203"
  },
  {
    "uid": "7229c1a8-cbed-4bfe-9e0e-c7a85e8534c0",
    "text": "Mary",
    "read": false,
    "created_at": "743"
  },
  {
    "uid": "7e5268e4-ce1d-4342-9ffe-51ca956206c6",
    "text": "Cherise",
    "read": false,
    "created_at": "618"
  },
  {
    "uid": "5d12eac5-5675-4857-a7a3-e9892c182720",
    "text": "Ulrika",
    "read": false,
    "created_at": "742"
  },
  {
    "uid": "00aa3a53-c904-4a1e-aca6-e1b76f0b466e",
    "text": "Sarah",
    "read": false,
    "created_at": "38"
  },
  {
    "uid": "4ca82275-f6b0-4725-b3dd-63dd5f647fb5",
    "text": "Rona",
    "read": false,
    "created_at": "121"
  },
  {
    "uid": "9a735a75-6a97-4e6b-9954-93416dcf2298",
    "text": "Laurene",
    "read": true,
    "created_at": "224"
  },
  {
    "uid": "ea9e2567-6db7-471e-acb4-3bbd3114304d",
    "text": "Ekaterina",
    "read": false,
    "created_at": "336"
  },
  {
    "uid": "e8f3ab72-298e-452c-924d-365724cb39a5",
    "text": "Torie",
    "read": false,
    "created_at": "844"
  },
  {
    "uid": "14f49086-1459-45a1-b210-a83c0e5ba8b1",
    "text": "Vally",
    "read": true,
    "created_at": "777"
  },
  {
    "uid": "8ecd1bc0-c21d-4a0f-852d-fcfa17615984",
    "text": "Kent",
    "read": true,
    "created_at": "30"
  },
  {
    "uid": "651c3e3e-1b59-4eab-83b5-9bc705724f5f",
    "text": "Brigham",
    "read": false,
    "created_at": "594"
  },
  {
    "uid": "ee72a484-b95d-4d9d-9491-fd6e7f4cf301",
    "text": "Fanchette",
    "read": false,
    "created_at": "133"
  },
  {
    "uid": "764550e6-09ac-4b73-bf6c-dd6f59811aa2",
    "text": "Melania",
    "read": false,
    "created_at": "219"
  },
  {
    "uid": "7899e90c-6abf-472a-95d9-293194dd13a1",
    "text": "Hakim",
    "read": false,
    "created_at": "449"
  }
]
